sprofiler/__init__.py
sprofiler/checkpoint.py
sprofiler/sprofiler.py
sprofiler-0.1.0.dist-info/LICENSE
sprofiler-0.1.0.dist-info/METADATA
sprofiler-0.1.0.dist-info/WHEEL
sprofiler-0.1.0.dist-info/top_level.txt
sprofiler-0.1.0.dist-info/RECORD
