Metadata-Version: 2.1
Name: sprofiler
Version: 0.1.0
Summary: Lightweight profiler with checkpoints
Home-page: https://github.com/bbrzycki/sprofiler
Author: Bryan Brzycki
Author-email: bbrzycki@berkeley.edu
License: UNKNOWN
Project-URL: Source, https://github.com/bbrzycki/sprofiler
Platform: UNKNOWN
Classifier: Programming Language :: Python :: 3
Classifier: License :: OSI Approved :: MIT License
Classifier: Operating System :: OS Independent
Requires-Dist: numpy (>=1.18.1)
